README.md
setup.py
py_auto_migrate/__init__.py
py_auto_migrate/cli.py
py_auto_migrate/migrator.py
py_auto_migrate/shell.py
py_auto_migrate.egg-info/PKG-INFO
py_auto_migrate.egg-info/SOURCES.txt
py_auto_migrate.egg-info/dependency_links.txt
py_auto_migrate.egg-info/entry_points.txt
py_auto_migrate.egg-info/requires.txt
py_auto_migrate.egg-info/top_level.txt
py_auto_migrate/base_models/__init__.py
py_auto_migrate/base_models/base_dynamodb.py
py_auto_migrate/base_models/base_mariadb.py
py_auto_migrate/base_models/base_mongodb.py
py_auto_migrate/base_models/base_mssql.py
py_auto_migrate/base_models/base_mysql.py
py_auto_migrate/base_models/base_oracle.py
py_auto_migrate/base_models/base_postgressql.py
py_auto_migrate/base_models/base_redis.py
py_auto_migrate/base_models/base_sqlite.py
py_auto_migrate/insert_models/__init__.py
py_auto_migrate/insert_models/insert_dynamodb.py
py_auto_migrate/insert_models/insert_mariadb.py
py_auto_migrate/insert_models/insert_mongodb.py
py_auto_migrate/insert_models/insert_mssql.py
py_auto_migrate/insert_models/insert_mysql.py
py_auto_migrate/insert_models/insert_oracle.py
py_auto_migrate/insert_models/insert_postgressql.py
py_auto_migrate/insert_models/insert_redis.py
py_auto_migrate/insert_models/insert_sqlite.py
py_auto_migrate/migrate_models/__init__.py
py_auto_migrate/migrate_models/migrate_dynamodb.py
py_auto_migrate/migrate_models/migrate_mariadb.py
py_auto_migrate/migrate_models/migrate_mongodb.py
py_auto_migrate/migrate_models/migrate_mssql.py
py_auto_migrate/migrate_models/migrate_mysql.py
py_auto_migrate/migrate_models/migrate_oracle.py
py_auto_migrate/migrate_models/migrate_postgresql.py
py_auto_migrate/migrate_models/migrate_redis.py
py_auto_migrate/migrate_models/migrate_sqlite.py