Metadata-Version: 2.1
Name: py-auto-migrate
Version: 0.2.3
Summary: A Tool For Transferring Data, Tables, And Datasets Between Different Databases.
Author: Kasra Khaksar
Author-email: kasrakhaksar17@gmail.com
Requires-Python: >=3.11
